{
	"npcs": [{
		"id": 0,
		"name": "Unicorn",
		"description": "It's a unicorn",
		"command": "",
		"attack": 21,
		"strength": 23,
		"hits": 19,
		"defense": 23,
		"ranged": false,
		"combatlvl": 21,
		"isMembers": 0,
		"attackable": 1,
		"aggressive": 0
	  },{
		"id": 1,
		"name": "Bob",
		"description": "_",
		"command": "",
		"attack": 2,
		"strength": 2,
		"hits": 3,
		"defense": 2,
		"ranged": false,
		"combatlvl": 2,
		"isMembers": 0,
		"attackable": 0,
		"aggressive": 0
	  },{
		"id": 2,
		"name": "Sheep",
		"description": "A very wooly sheep",
		"command": "",
		"attack": 0,
		"strength": 0,
		"hits": 3,
		"defense": 0,
		"ranged": false,
		"combatlvl": 0,
		"isMembers": 0,
		"attackable": 0,
		"aggressive": 0
	  },{
		"id": 3,
		"name": "Chicken",
		"description": "Yep definitely a chicken",
		"command": "",
		"attack": 3,
		"strength": 4,
		"hits": 3,
		"defense": 4,
		"ranged": false,
		"combatlvl": 3,
		"isMembers": 0,
		"attackable": 1,
		"aggressive": 0
	  },{
		"id": 4,
		"name": "Goblin",
		"description": "_",
		"command": "",
		"attack": 16,
		"strength": 13,
		"hits": 12,
		"defense": 14,
		"ranged": false,
		"combatlvl": 13,
		"isMembers": 0,
		"attackable": 1,
		"aggressive": 0
	  },{
		"id": 5,
		"name": "Hans",
		"description": "_",
		"command": "",
		"attack": 0,
		"strength": 0,
		"hits": 3,
		"defense": 0,
		"ranged": false,
		"combatlvl": 0,
		"isMembers": 0,
		"attackable": 1,
		"aggressive": 0
	  },{
		"id": 6,
		"name": "cow",
		"description": "It's a dairy cow",
		"command": "",
		"attack": 0,
		"strength": 0,
		"hits": 3,
		"defense": 0,
		"ranged": false,
		"combatlvl": 0,
		"isMembers": 0,
		"attackable": 0,
		"aggressive": 0
	  },{
		"id": 7,
		"name": "cook",
		"description": "The head cook of Lumbridge castle",
		"command": "",
		"attack": 20,
		"strength": 20,
		"hits": 3,
		"defense": 20,
		"ranged": false,
		"combatlvl": 15,
		"isMembers": 0,
		"attackable": 0,
		"aggressive": 0
	  },{
		"id": 8,
		"name": "Bear",
		"description": "Eek! A bear!",
		"command": "",
		"attack": 25,
		"strength": 26,
		"hits": 25,
		"defense": 23,
		"ranged": false,
		"combatlvl": 24,
		"isMembers": 0,
		"attackable": 1,
		"aggressive": 0
	  },{
		"id": 9,
		"name": "Priest",
		"description": "A priest of Saradomin",
		"command": "",
		"attack": 0,
		"strength": 0,
		"hits": 3,
		"defense": 0,
		"ranged": false,
		"combatlvl": 0,
		"isMembers": 0,
		"attackable": 0,
		"aggressive": 0
	  },{
		"id": 10,
		"name": "Urhney",
		"description": "He looks a little grumpy",
		"command": "",
		"attack": 10,
		"strength": 10,
		"hits": 3,
		"defense": 10,
		"ranged": false,
		"combatlvl": 8,
		"isMembers": 0,
		"attackable": 0,
		"aggressive": 0
	  },{
		"id": 11,
		"name": "Man",
		"description": "_",
		"command": "",
		"attack": 11,
		"strength": 11,
		"hits": 7,
		"defense": 8,
		"ranged": false,
		"combatlvl": 9,
		"isMembers": 0,
		"attackable": 1,
		"aggressive": 0
	  },{
		"id": 12,
		"name": "Bartender",
		"description": "I could get a beer off him",
		"command": "",
		"attack": 0,
		"strength": 0,
		"hits": 3,
		"defense": 0,
		"ranged": false,
		"combatlvl": 0,
		"isMembers": 0,
		"attackable": 0,
		"aggressive": 0
	  },{
		"id": 13,
		"name": "Camel",
		"description": "Oh its a camel",
		"command": "",
		"attack": 0,
		"strength": 0,
		"hits": 3,
		"defense": 0,
		"ranged": false,
		"combatlvl": 0,
		"isMembers": 0,
		"attackable": 0,
		"aggressive": 0
	  },{
		"id": 14,
		"name": "Gypsy",
		"description": "An old gypsy lady",
		"command": "",
		"attack": 0,
		"strength": 0,
		"hits": 3,
		"defense": 0,
		"ranged": false,
		"combatlvl": 0,
		"isMembers": 0,
		"attackable": 0,
		"aggressive": 0
	  },{
		"id": 15,
		"name": "Ghost",
		"description": "Ooh spooky",
		"command": "",
		"attack": 15,
		"strength": 15,
		"hits": 5,
		"defense": 15,
		"ranged": false,
		"combatlvl": 12,
		"isMembers": 0,
		"attackable": 0,
		"aggressive": 0
	  },{
		"id": 16,
		"name": "Sir Prysin",
		"description": "One of the king's knights",
		"command": "",
		"attack": 30,
		"strength": 20,
		"hits": 50,
		"defense": 60,
		"ranged": false,
		"combatlvl": 40,
		"isMembers": 0,
		"attackable": 0,
		"aggressive": 0
	  },{
		"id": 17,
		"name": "Traiborn the wizard",
		"description": "An old wizard",
		"command": "",
		"attack": 20,
		"strength": 10,
		"hits": 3,
		"defense": 15,
		"ranged": false,
		"combatlvl": 12,
		"isMembers": 0,
		"attackable": 0,
		"aggressive": 0
	  },{
		"id": 18,
		"name": "Captain Rovin",
		"description": "The head of the palace guard",
		"command": "",
		"attack": 40,
		"strength": 30,
		"hits": 65,
		"defense": 70,
		"ranged": false,
		"combatlvl": 51,
		"isMembers": 0,
		"attackable": 0,
		"aggressive": 0
	  },{
		"id": 19,
		"name": "Rat",
		"description": "_",
		"command": "",
		"attack": 10,
		"strength": 10,
		"hits": 5,
		"defense": 10,
		"ranged": false,
		"combatlvl": 8,
		"isMembers": 0,
		"attackable": 1,
		"aggressive": 0
	  },{
		"id": 20,
		"name": "Reldo",
		"description": "I think he's the librarian",
		"command": "",
		"attack": 20,
		"strength": 10,
		"hits": 3,
		"defense": 15,
		"ranged": false,
		"combatlvl": 12,
		"isMembers": 0,
		"attackable": 0,
		"aggressive": 0
	  },{
		"id": 21,
		"name": "mugger",
		"description": "_",
		"command": "",
		"attack": 15,
		"strength": 8,
		"hits": 8,
		"defense": 10,
		"ranged": false,
		"combatlvl": 10,
		"isMembers": 0,
		"attackable": 1,
		"aggressive": 1
	  },{
		"id": 22,
		"name": "Demon",
		"description": "_",
		"command": "",
		"attack": 0,
		"strength": 0,
		"hits": 5,
		"defense": 99,
		"ranged": false,
		"combatlvl": 26,
		"isMembers": 0,
		"attackable": 1,
		"aggressive": 0
	  },{
		"id": 23,
		"name": "Giant Spider",
		"description": "I think this spider has been genetically modified",
		"command": "",
		"attack": 10,
		"strength": 10,
		"hits": 5,
		"defense": 10,
		"ranged": false,
		"combatlvl": 8,
		"isMembers": 0,
		"attackable": 1,
		"aggressive": 0
	  },{
		"id": 24,
		"name": "Man",
		"description": "_",
		"command": "",
		"attack": 30,
		"strength": 30,
		"hits": 30,
		"defense": 30,
		"ranged": false,
		"combatlvl": 30,
		"isMembers": 0,
		"attackable": 1,
		"aggressive": 0
	  },{
		"id": 25,
		"name": "Jonny the beard",
		"description": "_",
		"command": "",
		"attack": 10,
		"strength": 5,
		"hits": 8,
		"defense": 20,
		"ranged": false,
		"combatlvl": 10,
		"isMembers": 0,
		"attackable": 1,
		"aggressive": 0
	  },{
		"id": 26,
		"name": "Baraek",
		"description": "A fur trader",
		"command": "",
		"attack": 30,
		"strength": 30,
		"hits": 30,
		"defense": 30,
		"ranged": false,
		"combatlvl": 30,
		"isMembers": 0,
		"attackable": 0,
		"aggressive": 0
	  },{
		"id": 27,
		"name": "Katrine",
		"description": "She doesn't look to friendly",
		"command": "",
		"attack": 35,
		"strength": 30,
		"hits": 10,
		"defense": 25,
		"ranged": false,
		"combatlvl": 25,
		"isMembers": 0,
		"attackable": 0,
		"aggressive": 0
	  },{
		"id": 28,
		"name": "Tramp",
		"description": "A scruffy looking chap",
		"command": "",
		"attack": 9,
		"strength": 7,
		"hits": 5,
		"defense": 8,
		"ranged": false,
		"combatlvl": 7,
		"isMembers": 0,
		"attackable": 0,
		"aggressive": 0
	  },{
		"id": 29,
		"name": "Rat",
		"description": "_",
		"command": "",
		"attack": 3,
		"strength": 2,
		"hits": 2,
		"defense": 4,
		"ranged": false,
		"combatlvl": 2,
		"isMembers": 0,
		"attackable": 1,
		"aggressive": 0
	  },{
		"id": 30,
		"name": "Romeo",
		"description": "He looks mildly confused",
		"command": "",
		"attack": 20,
		"strength": 40,
		"hits": 60,
		"defense": 60,
		"ranged": false,
		"combatlvl": 45,
		"isMembers": 0,
		"attackable": 0,
		"aggressive": 0
	  },{
		"id": 31,
		"name": "Juliet",
		"description": "She looks a little stressed",
		"command": "",
		"attack": 2,
		"strength": 2,
		"hits": 3,
		"defense": 4,
		"ranged": false,
		"combatlvl": 2,
		"isMembers": 0,
		"attackable": 0,
		"aggressive": 0
	  },{
		"id": 32,
		"name": "Father Lawrence",
		"description": "A kindly looking priest",
		"command": "",
		"attack": 0,
		"strength": 0,
		"hits": 3,
		"defense": 0,
		"ranged": false,
		"combatlvl": 0,
		"isMembers": 0,
		"attackable": 0,
		"aggressive": 0
	  },{
		"id": 33,
		"name": "Apothecary",
		"description": "I wonder if he has any good potions",
		"command": "",
		"attack": 10,
		"strength": 5,
		"hits": 7,
		"defense": 5,
		"ranged": false,
		"combatlvl": 6,
		"isMembers": 0,
		"attackable": 0,
		"aggressive": 0
	  },{
		"id": 34,
		"name": "spider",
		"description": "_",
		"command": "",
		"attack": 5,
		"strength": 1,
		"hits": 2,
		"defense": 2,
		"ranged": false,
		"combatlvl": 2,
		"isMembers": 0,
		"attackable": 1,
		"aggressive": 0
	  },{
		"id": 35,
		"name": "Delrith",
		"description": "_",
		"command": "",
		"attack": 35,
		"strength": 30,
		"hits": 7,
		"defense": 20,
		"ranged": false,
		"combatlvl": 23,
		"isMembers": 0,
		"attackable": 1,
		"aggressive": 0
	  },{
		"id": 36,
		"name": "Veronica",
		"description": "She doesn't look too happy",
		"command": "",
		"attack": 1,
		"strength": 1,
		"hits": 5,
		"defense": 1,
		"ranged": false,
		"combatlvl": 2,
		"isMembers": 0,
		"attackable": 0,
		"aggressive": 0
	  },{
		"id": 37,
		"name": "Weaponsmaster",
		"description": "_",
		"command": "",
		"attack": 35,
		"strength": 28,
		"hits": 20,
		"defense": 20,
		"ranged": false,
		"combatlvl": 25,
		"isMembers": 0,
		"attackable": 1,
		"aggressive": 0
	  },{
		"id": 38,
		"name": "Professor Oddenstein",
		"description": "A mad scientist if I ever saw one",
		"command": "",
		"attack": 3,
		"strength": 3,
		"hits": 7,
		"defense": 3,
		"ranged": false,
		"combatlvl": 4,
		"isMembers": 0,
		"attackable": 0,
		"aggressive": 0
	  },{
		"id": 39,
		"name": "Curator",
		"description": "He looks like he's daydreaming",
		"command": "",
		"attack": 3,
		"strength": 2,
		"hits": 3,
		"defense": 2,
		"ranged": false,
		"combatlvl": 2,
		"isMembers": 0,
		"attackable": 0,
		"aggressive": 0
	  },{
		"id": 40,
		"name": "skeleton",
		"description": "_",
		"command": "",
		"attack": 24,
		"strength": 23,
		"hits": 17,
		"defense": 20,
		"ranged": false,
		"combatlvl": 21,
		"isMembers": 0,
		"attackable": 1,
		"aggressive": 0
	  },{
		"id": 41,
		"name": "zombie",
		"description": "_",
		"command": "",
		"attack": 23,
		"strength": 23,
		"hits": 24,
		"defense": 28,
		"ranged": false,
		"combatlvl": 24,
		"isMembers": 0,
		"attackable": 1,
		"aggressive": 1
	  },{
		"id": 42,
		"name": "king",
		"description": "King Roald the VIII",
		"command": "",
		"attack": 15,
		"strength": 15,
		"hits": 30,
		"defense": 60,
		"ranged": false,
		"combatlvl": 30,
		"isMembers": 0,
		"attackable": 0,
		"aggressive": 0
	  },{
		"id": 43,
		"name": "bat",
		"description": "_",
		"command": "",
		"attack": 5,
		"strength": 1,
		"hits": 2,
		"defense": 22,
		"ranged": false,
		"combatlvl": 7,
		"isMembers": 0,
		"attackable": 0,
		"aggressive": 0
	  },{
		"id": 44,
		"name": "Bartender",
		"description": "A friendly barman",
		"command": "",
		"attack": 0,
		"strength": 0,
		"hits": 3,
		"defense": 0,
		"ranged": false,
		"combatlvl": 0,
		"isMembers": 0,
		"attackable": 0,
		"aggressive": 0
	  },{
		"id": 45,
		"name": "skeleton",
		"description": "_",
		"command": "",
		"attack": 32,
		"strength": 35,
		"hits": 29,
		"defense": 30,
		"ranged": false,
		"combatlvl": 31,
		"isMembers": 0,
		"attackable": 1,
		"aggressive": 1
	  },{
		"id": 46,
		"name": "skeleton",
		"description": "_",
		"command": "",
		"attack": 27,
		"strength": 28,
		"hits": 24,
		"defense": 24,
		"ranged": false,
		"combatlvl": 25,
		"isMembers": 0,
		"attackable": 1,
		"aggressive": 1
	  },{
		"id": 47,
		"name": "Rat",
		"description": "_",
		"command": "",
		"attack": 16,
		"strength": 15,
		"hits": 10,
		"defense": 12,
		"ranged": false,
		"combatlvl": 13,
		"isMembers": 0,
		"attackable": 1,
		"aggressive": 1
	  },{
		"id": 48,
		"name": "Horvik the Armourer",
		"description": "He looks strong",
		"command": "",
		"attack": 15,
		"strength": 6,
		"hits": 22,
		"defense": 22,
		"ranged": false,
		"combatlvl": 16,
		"isMembers": 0,
		"attackable": 0,
		"aggressive": 0
	  },{
		"id": 49,
		"name": "Bear",
		"description": "A stuffed bear",
		"command": "",
		"attack": 0,
		"strength": 0,
		"hits": 3,
		"defense": 0,
		"ranged": false,
		"combatlvl": 0,
		"isMembers": 0,
		"attackable": 0,
		"aggressive": 0
	  },{
		"id": 50,
		"name": "skeleton",
		"description": "_",
		"command": "",
		"attack": 20,
		"strength": 21,
		"hits": 18,
		"defense": 18,
		"ranged": false,
		"combatlvl": 19,
		"isMembers": 0,
		"attackable": 1,
		"aggressive": 1
	  },{
		"id": 51,
		"name": "Shopkeeper",
		"description": "Maybe he'd like to buy some of my junk",
		"command": "",
		"attack": 0,
		"strength": 0,
		"hits": 3,
		"defense": 0,
		"ranged": false,
		"combatlvl": 0,
		"isMembers": 0,
		"attackable": 0,
		"aggressive": 0
	  },{
		"id": 52,
		"name": "zombie",
		"description": "_",
		"command": "",
		"attack": 18,
		"strength": 19,
		"hits": 22,
		"defense": 20,
		"ranged": false,
		"combatlvl": 19,
		"isMembers": 0,
		"attackable": 1,
		"aggressive": 0
	  },{
		"id": 53,
		"name": "Ghost",
		"description": "Ooh spooky",
		"command": "",
		"attack": 23,
		"strength": 23,
		"hits": 25,
		"defense": 30,
		"ranged": false,
		"combatlvl": 25,
		"isMembers": 0,
		"attackable": 1,
		"aggressive": 1
	  },{
		"id": 54,
		"name": "Aubury",
		"description": "I think he might be a shop keeper",
		"command": "",
		"attack": 0,
		"strength": 0,
		"hits": 3,
		"defense": 0,
		"ranged": false,
		"combatlvl": 0,
		"isMembers": 0,
		"attackable": 0,
		"aggressive": 0
	  },{
		"id": 55,
		"name": "Shopkeeper",
		"description": "I wonder what he's got for sale",
		"command": "",
		"attack": 0,
		"strength": 0,
		"hits": 3,
		"defense": 0,
		"ranged": false,
		"combatlvl": 0,
		"isMembers": 0,
		"attackable": 0,
		"aggressive": 0
	  },{
		"id": 56,
		"name": "shopkeeper",
		"description": "I can buy swords off him",
		"command": "",
		"attack": 0,
		"strength": 0,
		"hits": 3,
		"defense": 0,
		"ranged": false,
		"combatlvl": 0,
		"isMembers": 0,
		"attackable": 0,
		"aggressive": 0
	  },{
		"id": 57,
		"name": "Darkwizard",
		"description": "_",
		"command": "",
		"attack": 15,
		"strength": 12,
		"hits": 12,
		"defense": 15,
		"ranged": false,
		"combatlvl": 13,
		"isMembers": 0,
		"attackable": 1,
		"aggressive": 1
	  },{
		"id": 58,
		"name": "lowe",
		"description": "The owner of the archery store",
		"command": "",
		"attack": 0,
		"strength": 0,
		"hits": 3,
		"defense": 0,
		"ranged": false,
		"combatlvl": 0,
		"isMembers": 0,
		"attackable": 0,
		"aggressive": 0
	  },{
		"id": 59,
		"name": "Thessalia",
		"description": "A young shop assistant",
		"command": "",
		"attack": 0,
		"strength": 0,
		"hits": 3,
		"defense": 0,
		"ranged": false,
		"combatlvl": 0,
		"isMembers": 0,
		"attackable": 0,
		"aggressive": 0
	  },{
		"id": 60,
		"name": "Darkwizard",
		"description": "_",
		"command": "",
		"attack": 27,
		"strength": 27,
		"hits": 24,
		"defense": 24,
		"ranged": false,
		"combatlvl": 25,
		"isMembers": 0,
		"attackable": 1,
		"aggressive": 1
	  },{
		"id": 61,
		"name": "Giant",
		"description": "_",
		"command": "",
		"attack": 37,
		"strength": 40,
		"hits": 35,
		"defense": 36,
		"ranged": false,
		"combatlvl": 37,
		"isMembers": 0,
		"attackable": 1,
		"aggressive": 1
	  },{
		"id": 62,
		"name": "Goblin",
		"description": "_",
		"command": "",
		"attack": 8,
		"strength": 9,
		"hits": 5,
		"defense": 9,
		"ranged": false,
		"combatlvl": 7,
		"isMembers": 0,
		"attackable": 1,
		"aggressive": 0
	  },{
		"id": 63,
		"name": "farmer",
		"description": "_",
		"command": "",
		"attack": 15,
		"strength": 18,
		"hits": 12,
		"defense": 16,
		"ranged": false,
		"combatlvl": 15,
		"isMembers": 0,
		"attackable": 1,
		"aggressive": 0
	  },{
		"id": 64,
		"name": "Thief",
		"description": "_",
		"command": "",
		"attack": 24,
		"strength": 23,
		"hits": 17,
		"defense": 22,
		"ranged": false,
		"combatlvl": 21,
		"isMembers": 0,
		"attackable": 1,
		"aggressive": 0
	  },{
		"id": 65,
		"name": "Guard",
		"description": "_",
		"command": "",
		"attack": 31,
		"strength": 31,
		"hits": 22,
		"defense": 30,
		"ranged": false,
		"combatlvl": 28,
		"isMembers": 0,
		"attackable": 1,
		"aggressive": 0
	  },{
		"id": 66,
		"name": "Black Knight",
		"description": "_",
		"command": "",
		"attack": 45,
		"strength": 48,
		"hits": 42,
		"defense": 50,
		"ranged": false,
		"combatlvl": 46,
		"isMembers": 0,
		"attackable": 1,
		"aggressive": 0
	  },{
		"id": 67,
		"name": "Hobgoblin",
		"description": "_",
		"command": "",
		"attack": 32,
		"strength": 34,
		"hits": 29,
		"defense": 34,
		"ranged": false,
		"combatlvl": 32,
		"isMembers": 0,
		"attackable": 1,
		"aggressive": 1
	  },{
		"id": 68,
		"name": "zombie",
		"description": "_",
		"command": "",
		"attack": 32,
		"strength": 35,
		"hits": 30,
		"defense": 31,
		"ranged": false,
		"combatlvl": 32,
		"isMembers": 0,
		"attackable": 1,
		"aggressive": 1
	  },{
		"id": 69,
		"name": "Zaff",
		"description": "He trades in staffs",
		"command": "",
		"attack": 0,
		"strength": 0,
		"hits": 3,
		"defense": 0,
		"ranged": false,
		"combatlvl": 0,
		"isMembers": 0,
		"attackable": 0,
		"aggressive": 0
	  },{
		"id": 70,
		"name": "Scorpion",
		"description": "_",
		"command": "",
		"attack": 21,
		"strength": 22,
		"hits": 17,
		"defense": 24,
		"ranged": false,
		"combatlvl": 21,
		"isMembers": 0,
		"attackable": 1,
		"aggressive": 1
	  },{
		"id": 71,
		"name": "silk trader",
		"description": "He sells silk",
		"command": "",
		"attack": 0,
		"strength": 0,
		"hits": 3,
		"defense": 0,
		"ranged": false,
		"combatlvl": 0,
		"isMembers": 0,
		"attackable": 0,
		"aggressive": 0
	  },{
		"id": 72,
		"name": "Man",
		"description": "_",
		"command": "",
		"attack": 11,
		"strength": 11,
		"hits": 7,
		"defense": 8,
		"ranged": false,
		"combatlvl": 9,
		"isMembers": 0,
		"attackable": 1,
		"aggressive": 0
	  },{
		"id": 73,
		"name": "Guide",
		"description": "He gives hints to new adventurers",
		"command": "",
		"attack": 0,
		"strength": 0,
		"hits": 7,
		"defense": 0,
		"ranged": false,
		"combatlvl": 1,
		"isMembers": 0,
		"attackable": 0,
		"aggressive": 0
	  },{
		"id": 74,
		"name": "Giant Spider",
		"description": "I think this spider has been genetically modified",
		"command": "",
		"attack": 30,
		"strength": 34,
		"hits": 32,
		"defense": 31,
		"ranged": false,
		"combatlvl": 31,
		"isMembers": 0,
		"attackable": 1,
		"aggressive": 1
	  },{
		"id": 75,
		"name": "Peksa",
		"description": "A helmet salesman",
		"command": "",
		"attack": 11,
		"strength": 11,
		"hits": 7,
		"defense": 8,
		"ranged": false,
		"combatlvl": 9,
		"isMembers": 0,
		"attackable": 0,
		"aggressive": 0
	  },{
		"id": 76,
		"name": "Barbarian",
		"description": "_",
		"command": "",
		"attack": 18,
		"strength": 18,
		"hits": 14,
		"defense": 15,
		"ranged": false,
		"combatlvl": 16,
		"isMembers": 0,
		"attackable": 1,
		"aggressive": 0
	  },{
		"id": 77,
		"name": "Fred the farmer",
		"description": "An old farmer",
		"command": "",
		"attack": 11,
		"strength": 11,
		"hits": 7,
		"defense": 8,
		"ranged": false,
		"combatlvl": 9,
		"isMembers": 0,
		"attackable": 0,
		"aggressive": 0
	  },{
		"id": 78,
		"name": "Gunthor the Brave",
		"description": "_",
		"command": "",
		"attack": 37,
		"strength": 38,
		"hits": 35,
		"defense": 40,
		"ranged": false,
		"combatlvl": 37,
		"isMembers": 0,
		"attackable": 1,
		"aggressive": 0
	  },{
		"id": 79,
		"name": "Witch",
		"description": "She's got warts",
		"command": "",
		"attack": 35,
		"strength": 30,
		"hits": 10,
		"defense": 25,
		"ranged": false,
		"combatlvl": 25,
		"isMembers": 0,
		"attackable": 1,
		"aggressive": 0
	  },{
		"id": 80,
		"name": "Ghost",
		"description": "Ooh spooky",
		"command": "",
		"attack": 23,
		"strength": 23,
		"hits": 25,
		"defense": 30,
		"ranged": false,
		"combatlvl": 25,
		"isMembers": 0,
		"attackable": 1,
		"aggressive": 0
	  },{
		"id": 81,
		"name": "Wizard",
		"description": "An old wizard",
		"command": "",
		"attack": 18,
		"strength": 18,
		"hits": 14,
		"defense": 15,
		"ranged": false,
		"combatlvl": 16,
		"isMembers": 0,
		"attackable": 1,
		"aggressive": 0
	  },{
		"id": 82,
		"name": "Shop Assistant",
		"description": "Maybe he'd like to buy some of my junk",
		"command": "",
		"attack": 0,
		"strength": 0,
		"hits": 3,
		"defense": 0,
		"ranged": false,
		"combatlvl": 0,
		"isMembers": 0,
		"attackable": 0,
		"aggressive": 0
	  },{
		"id": 83,
		"name": "Shop Assistant",
		"description": "Maybe he'd like to buy some of my junk",
		"command": "",
		"attack": 0,
		"strength": 0,
		"hits": 3,
		"defense": 0,
		"ranged": false,
		"combatlvl": 0,
		"isMembers": 0,
		"attackable": 0,
		"aggressive": 0
	  },{
		"id": 84,
		"name": "Zeke",
		"description": "He sells Scimitars",
		"command": "",
		"attack": 0,
		"strength": 0,
		"hits": 3,
		"defense": 0,
		"ranged": false,
		"combatlvl": 0,
		"isMembers": 0,
		"attackable": 0,
		"aggressive": 0
	  },{
		"id": 85,
		"name": "Louie Legs",
		"description": "He might want to sell something",
		"command": "",
		"attack": 0,
		"strength": 0,
		"hits": 3,
		"defense": 0,
		"ranged": false,
		"combatlvl": 0,
		"isMembers": 0,
		"attackable": 0,
		"aggressive": 0
	  },{
		"id": 86,
		"name": "Warrior",
		"description": "_",
		"command": "",
		"attack": 20,
		"strength": 18,
		"hits": 19,
		"defense": 17,
		"ranged": false,
		"combatlvl": 18,
		"isMembers": 0,
		"attackable": 1,
		"aggressive": 0
	  },{
		"id": 87,
		"name": "Shopkeeper",
		"description": "I wonder what he's got for sale",
		"command": "",
		"attack": 0,
		"strength": 0,
		"hits": 3,
		"defense": 0,
		"ranged": false,
		"combatlvl": 0,
		"isMembers": 0,
		"attackable": 0,
		"aggressive": 0
	  },{
		"id": 88,
		"name": "Shop Assistant",
		"description": "Maybe she'd like to buy some of my junk",
		"command": "",
		"attack": 0,
		"strength": 0,
		"hits": 3,
		"defense": 0,
		"ranged": false,
		"combatlvl": 0,
		"isMembers": 0,
		"attackable": 0,
		"aggressive": 0
	  },{
		"id": 89,
		"name": "Highwayman",
		"description": "_",
		"command": "",
		"attack": 14,
		"strength": 13,
		"hits": 13,
		"defense": 15,
		"ranged": false,
		"combatlvl": 13,
		"isMembers": 0,
		"attackable": 1,
		"aggressive": 1
	  },{
		"id": 90,
		"name": "Kebab Seller",
		"description": "_",
		"command": "",
		"attack": 0,
		"strength": 0,
		"hits": 3,
		"defense": 0,
		"ranged": false,
		"combatlvl": 0,
		"isMembers": 0,
		"attackable": 0,
		"aggressive": 0
	  },{
		"id": 91,
		"name": "Chicken",
		"description": "Yep definitely a chicken",
		"command": "",
		"attack": 3,
		"strength": 4,
		"hits": 3,
		"defense": 4,
		"ranged": false,
		"combatlvl": 3,
		"isMembers": 0,
		"attackable": 0,
		"aggressive": 0
	  },{
		"id": 92,
		"name": "Ernest",
		"description": "A former chicken",
		"command": "",
		"attack": 3,
		"strength": 3,
		"hits": 3,
		"defense": 3,
		"ranged": false,
		"combatlvl": 3,
		"isMembers": 0,
		"attackable": 0,
		"aggressive": 0
	  },{
		"id": 93,
		"name": "Monk",
		"description": "A Peaceful monk",
		"command": "",
		"attack": 12,
		"strength": 12,
		"hits": 15,
		"defense": 13,
		"ranged": false,
		"combatlvl": 13,
		"isMembers": 0,
		"attackable": 1,
		"aggressive": 0
	  },{
		"id": 94,
		"name": "Dwarf",
		"description": "A short angry guy",
		"command": "",
		"attack": 20,
		"strength": 20,
		"hits": 16,
		"defense": 17,
		"ranged": false,
		"combatlvl": 18,
		"isMembers": 0,
		"attackable": 1,
		"aggressive": 0
	  },{
		"id": 95,
		"name": "Banker",
		"description": "He can look after my money",
		"command": "",
		"attack": 11,
		"strength": 11,
		"hits": 7,
		"defense": 8,
		"ranged": false,
		"combatlvl": 9,
		"isMembers": 0,
		"attackable": 0,
		"aggressive": 0
	  },{
		"id": 96,
		"name": "Count Draynor",
		"description": "A vicious vampire",
		"command": "",
		"attack": 40,
		"strength": 35,
		"hits": 35,
		"defense": 65,
		"ranged": false,
		"combatlvl": 43,
		"isMembers": 0,
		"attackable": 1,
		"aggressive": 0
	  },{
		"id": 97,
		"name": "Morgan",
		"description": "_",
		"command": "",
		"attack": 11,
		"strength": 11,
		"hits": 7,
		"defense": 8,
		"ranged": false,
		"combatlvl": 9,
		"isMembers": 0,
		"attackable": 0,
		"aggressive": 0
	  },{
		"id": 98,
		"name": "Dr Harlow",
		"description": "_",
		"command": "",
		"attack": 11,
		"strength": 11,
		"hits": 7,
		"defense": 8,
		"ranged": false,
		"combatlvl": 9,
		"isMembers": 0,
		"attackable": 0,
		"aggressive": 0
	  },{
		"id": 99,
		"name": "Deadly Red spider",
		"description": "I think this spider has been genetically modified",
		"command": "",
		"attack": 40,
		"strength": 35,
		"hits": 35,
		"defense": 36,
		"ranged": false,
		"combatlvl": 36,
		"isMembers": 0,
		"attackable": 1,
		"aggressive": 1
	  },{
		"id": 100,
		"name": "Guard",
		"description": "_",
		"command": "",
		"attack": 31,
		"strength": 31,
		"hits": 22,
		"defense": 30,
		"ranged": false,
		"combatlvl": 28,
		"isMembers": 0,
		"attackable": 1,
		"aggressive": 0
	  },{
		"id": 101,
		"name": "Cassie",
		"description": "She sells shields",
		"command": "",
		"attack": 35,
		"strength": 30,
		"hits": 10,
		"defense": 25,
		"ranged": false,
		"combatlvl": 25,
		"isMembers": 0,
		"attackable": 0,
		"aggressive": 0
	  },{
		"id": 102,
		"name": "White Knight",
		"description": "_",
		"command": "",
		"attack": 55,
		"strength": 58,
		"hits": 52,
		"defense": 60,
		"ranged": false,
		"combatlvl": 56,
		"isMembers": 0,
		"attackable": 1,
		"aggressive": 0
	  },{
		"id": 103,
		"name": "Ranael",
		"description": "A shopkeeper of some sort",
		"command": "",
		"attack": 35,
		"strength": 30,
		"hits": 10,
		"defense": 25,
		"ranged": false,
		"combatlvl": 25,
		"isMembers": 0,
		"attackable": 0,
		"aggressive": 0
	  },{
		"id": 104,
		"name": "Moss Giant",
		"description": "_",
		"command": "",
		"attack": 62,
		"strength": 65,
		"hits": 60,
		"defense": 61,
		"ranged": false,
		"combatlvl": 62,
		"isMembers": 0,
		"attackable": 1,
		"aggressive": 1
	  },{
		"id": 105,
		"name": "Shopkeeper",
		"description": "I wonder what he's got for sale",
		"command": "",
		"attack": 0,
		"strength": 0,
		"hits": 3,
		"defense": 0,
		"ranged": false,
		"combatlvl": 0,
		"isMembers": 0,
		"attackable": 0,
		"aggressive": 0
	  },{
		"id": 106,
		"name": "Shop Assistant",
		"description": "Maybe he'd like to buy some of my junk",
		"command": "",
		"attack": 0,
		"strength": 0,
		"hits": 3,
		"defense": 0,
		"ranged": false,
		"combatlvl": 0,
		"isMembers": 0,
		"attackable": 0,
		"aggressive": 0
	  },{
		"id": 107,
		"name": "Witch",
		"description": "She's got warts",
		"command": "",
		"attack": 35,
		"strength": 30,
		"hits": 10,
		"defense": 25,
		"ranged": false,
		"combatlvl": 25,
		"isMembers": 0,
		"attackable": 0,
		"aggressive": 0
	  },{
		"id": 108,
		"name": "Black Knight",
		"description": "_",
		"command": "",
		"attack": 45,
		"strength": 48,
		"hits": 42,
		"defense": 50,
		"ranged": false,
		"combatlvl": 46,
		"isMembers": 0,
		"attackable": 1,
		"aggressive": 0
	  },{
		"id": 109,
		"name": "Greldo",
		"description": "_",
		"command": "",
		"attack": 8,
		"strength": 9,
		"hits": 5,
		"defense": 9,
		"ranged": false,
		"combatlvl": 7,
		"isMembers": 0,
		"attackable": 1,
		"aggressive": 0
	  },{
		"id": 110,
		"name": "Sir Amik Varze",
		"description": "The leader of the white knights",
		"command": "",
		"attack": 55,
		"strength": 58,
		"hits": 52,
		"defense": 60,
		"ranged": false,
		"combatlvl": 56,
		"isMembers": 0,
		"attackable": 0,
		"aggressive": 0
	  },{
		"id": 111,
		"name": "Guildmaster",
		"description": "He's in charge of this place",
		"command": "",
		"attack": 40,
		"strength": 40,
		"hits": 40,
		"defense": 40,
		"ranged": false,
		"combatlvl": 40,
		"isMembers": 0,
		"attackable": 0,
		"aggressive": 0
	  },{
		"id": 112,
		"name": "Valaine",
		"description": "_She runs the champion's store",
		"command": "",
		"attack": 35,
		"strength": 30,
		"hits": 10,
		"defense": 25,
		"ranged": false,
		"combatlvl": 25,
		"isMembers": 0,
		"attackable": 0,
		"aggressive": 0
	  },{
		"id": 113,
		"name": "Drogo",
		"description": "He runs a mining store",
		"command": "",
		"attack": 20,
		"strength": 20,
		"hits": 16,
		"defense": 17,
		"ranged": false,
		"combatlvl": 18,
		"isMembers": 0,
		"attackable": 0,
		"aggressive": 0
	  },{
		"id": 114,
		"name": "Imp",
		"description": "_",
		"command": "",
		"attack": 4,
		"strength": 5,
		"hits": 8,
		"defense": 4,
		"ranged": false,
		"combatlvl": 5,
		"isMembers": 0,
		"attackable": 1,
		"aggressive": 0
	  },{
		"id": 115,
		"name": "Flynn",
		"description": "The mace salesman",
		"command": "",
		"attack": 15,
		"strength": 6,
		"hits": 22,
		"defense": 22,
		"ranged": false,
		"combatlvl": 16,
		"isMembers": 0,
		"attackable": 0,
		"aggressive": 0
	  },{
		"id": 116,
		"name": "Wyson the gardener",
		"description": "An old gardener",
		"command": "",
		"attack": 10,
		"strength": 8,
		"hits": 7,
		"defense": 8,
		"ranged": false,
		"combatlvl": 8,
		"isMembers": 0,
		"attackable": 1,
		"aggressive": 0
	  },{
		"id": 117,
		"name": "Wizard Mizgog",
		"description": "An old wizard",
		"command": "",
		"attack": 20,
		"strength": 10,
		"hits": 3,
		"defense": 15,
		"ranged": false,
		"combatlvl": 12,
		"isMembers": 0,
		"attackable": 0,
		"aggressive": 0
	  },{
		"id": 118,
		"name": "Prince Ali",
		"description": "A young prince",
		"command": "",
		"attack": 20,
		"strength": 20,
		"hits": 20,
		"defense": 20,
		"ranged": false,
		"combatlvl": 20,
		"isMembers": 0,
		"attackable": 0,
		"aggressive": 0
	  },{
		"id": 119,
		"name": "Hassan",
		"description": "the Chancellor to the emir",
		"command": "",
		"attack": 20,
		"strength": 20,
		"hits": 20,
		"defense": 20,
		"ranged": false,
		"combatlvl": 20,
		"isMembers": 0,
		"attackable": 0,
		"aggressive": 0
	  },{
		"id": 120,
		"name": "Osman",
		"description": "He looks a little shifty",
		"command": "",
		"attack": 20,
		"strength": 20,
		"hits": 20,
		"defense": 20,
		"ranged": false,
		"combatlvl": 20,
		"isMembers": 0,
		"attackable": 0,
		"aggressive": 0
	  },{
		"id": 121,
		"name": "Joe",
		"description": "Lady Keli's head guard",
		"command": "",
		"attack": 40,
		"strength": 40,
		"hits": 40,
		"defense": 40,
		"ranged": false,
		"combatlvl": 40,
		"isMembers": 0,
		"attackable": 0,
		"aggressive": 0
	  },{
		"id": 122,
		"name": "Leela",
		"description": "She comes from Al Kharid",
		"command": "",
		"attack": 20,
		"strength": 20,
		"hits": 20,
		"defense": 20,
		"ranged": false,
		"combatlvl": 20,
		"isMembers": 0,
		"attackable": 0,
		"aggressive": 0
	  },{
		"id": 123,
		"name": "Lady Keli",
		"description": "An Infamous bandit",
		"command": "",
		"attack": 20,
		"strength": 20,
		"hits": 20,
		"defense": 20,
		"ranged": false,
		"combatlvl": 20,
		"isMembers": 0,
		"attackable": 0,
		"aggressive": 0
	  },{
		"id": 124,
		"name": "Ned",
		"description": "An old sailor",
		"command": "",
		"attack": 20,
		"strength": 20,
		"hits": 20,
		"defense": 20,
		"ranged": false,
		"combatlvl": 20,
		"isMembers": 0,
		"attackable": 0,
		"aggressive": 0
	  },{
		"id": 125,
		"name": "Aggie",
		"description": "A witch",
		"command": "",
		"attack": 35,
		"strength": 30,
		"hits": 10,
		"defense": 25,
		"ranged": false,
		"combatlvl": 25,
		"isMembers": 0,
		"attackable": 0,
		"aggressive": 0
	  },{
		"id": 126,
		"name": "Prince  Ali",
		"description": "That is an effective disguise",
		"command": "",
		"attack": 10,
		"strength": 10,
		"hits": 10,
		"defense": 10,
		"ranged": false,
		"combatlvl": 10,
		"isMembers": 0,
		"attackable": 0,
		"aggressive": 0
	  },{
		"id": 127,
		"name": "Jailguard",
		"description": "I wonder what he's guarding",
		"command": "",
		"attack": 34,
		"strength": 36,
		"hits": 32,
		"defense": 34,
		"ranged": false,
		"combatlvl": 34,
		"isMembers": 0,
		"attackable": 1,
		"aggressive": 0
	  },{
		"id": 128,
		"name": "One-eyed Frank",
		"description": "A pirate",
		"command": "",
		"attack": 35,
		"strength": 30,
		"hits": 10,
		"defense": 25,
		"ranged": false,
		"combatlvl": 25,
		"isMembers": 0,
		"attackable": 0,
		"aggressive": 0
	  },{
		"id": 129,
		"name": "Wydin",
		"description": "A grocer",
		"command": "",
		"attack": 0,
		"strength": 0,
		"hits": 3,
		"defense": 0,
		"ranged": false,
		"combatlvl": 0,
		"isMembers": 0,
		"attackable": 0,
		"aggressive": 0
	  },{
		"id": 130,
		"name": "shop assistant",
		"description": "I can buy swords off him",
		"command": "",
		"attack": 0,
		"strength": 0,
		"hits": 3,
		"defense": 0,
		"ranged": false,
		"combatlvl": 0,
		"isMembers": 0,
		"attackable": 0,
		"aggressive": 0
	  },{
		"id": 131,
		"name": "Brian",
		"description": "An axe seller",
		"command": "",
		"attack": 0,
		"strength": 0,
		"hits": 3,
		"defense": 0,
		"ranged": false,
		"combatlvl": 0,
		"isMembers": 0,
		"attackable": 0,
		"aggressive": 0
	  },{
		"id": 132,
		"name": "squire",
		"description": "A young squire",
		"command": "",
		"attack": 0,
		"strength": 0,
		"hits": 3,
		"defense": 0,
		"ranged": false,
		"combatlvl": 0,
		"isMembers": 0,
		"attackable": 0,
		"aggressive": 0
	  },{
		"id": 133,
		"name": "Head chef",
		"description": "He looks after the chef's guild",
		"command": "",
		"attack": 20,
		"strength": 20,
		"hits": 3,
		"defense": 20,
		"ranged": false,
		"combatlvl": 15,
		"isMembers": 0,
		"attackable": 0,
		"aggressive": 0
	  },{
		"id": 134,
		"name": "Thurgo",
		"description": "A short angry guy",
		"command": "",
		"attack": 20,
		"strength": 20,
		"hits": 16,
		"defense": 17,
		"ranged": false,
		"combatlvl": 18,
		"isMembers": 0,
		"attackable": 0,
		"aggressive": 0
	  },{
		"id": 135,
		"name": "Ice Giant",
		"description": "_",
		"command": "",
		"attack": 67,
		"strength": 70,
		"hits": 70,
		"defense": 66,
		"ranged": false,
		"combatlvl": 68,
		"isMembers": 0,
		"attackable": 1,
		"aggressive": 1
	  },{
		"id": 136,
		"name": "King Scorpion",
		"description": "_",
		"command": "",
		"attack": 40,
		"strength": 39,
		"hits": 30,
		"defense": 38,
		"ranged": false,
		"combatlvl": 36,
		"isMembers": 0,
		"attackable": 1,
		"aggressive": 1
	  },{
		"id": 137,
		"name": "Pirate",
		"description": "A vicious pirate",
		"command": "",
		"attack": 35,
		"strength": 30,
		"hits": 20,
		"defense": 25,
		"ranged": false,
		"combatlvl": 27,
		"isMembers": 0,
		"attackable": 1,
		"aggressive": 1
	  },{
		"id": 138,
		"name": "Sir Vyvin",
		"description": "One of the white knights of Falador",
		"command": "",
		"attack": 55,
		"strength": 58,
		"hits": 52,
		"defense": 60,
		"ranged": false,
		"combatlvl": 56,
		"isMembers": 0,
		"attackable": 0,
		"aggressive": 0
	  },{
		"id": 139,
		"name": "Monk of Zamorak",
		"description": "An evil cleric",
		"command": "",
		"attack": 28,
		"strength": 28,
		"hits": 30,
		"defense": 32,
		"ranged": false,
		"combatlvl": 29,
		"isMembers": 0,
		"attackable": 1,
		"aggressive": 0
	  },{
		"id": 140,
		"name": "Monk of Zamorak",
		"description": "An evil cleric",
		"command": "",
		"attack": 18,
		"strength": 18,
		"hits": 20,
		"defense": 22,
		"ranged": false,
		"combatlvl": 19,
		"isMembers": 0,
		"attackable": 1,
		"aggressive": 0
	  },{
		"id": 141,
		"name": "Wayne",
		"description": "An armourer",
		"command": "",
		"attack": 15,
		"strength": 6,
		"hits": 22,
		"defense": 22,
		"ranged": false,
		"combatlvl": 16,
		"isMembers": 0,
		"attackable": 0,
		"aggressive": 0
	  },{
		"id": 142,
		"name": "Barmaid",
		"description": "a pretty barmaid",
		"command": "",
		"attack": 35,
		"strength": 30,
		"hits": 10,
		"defense": 25,
		"ranged": false,
		"combatlvl": 25,
		"isMembers": 0,
		"attackable": 0,
		"aggressive": 0
	  },{
		"id": 143,
		"name": "Dwarven shopkeeper",
		"description": "I wonder if he wants to buy any of my junk",
		"command": "",
		"attack": 20,
		"strength": 20,
		"hits": 16,
		"defense": 17,
		"ranged": false,
		"combatlvl": 18,
		"isMembers": 0,
		"attackable": 0,
		"aggressive": 0
	  },{
		"id": 144,
		"name": "Doric",
		"description": "A dwarven smith",
		"command": "",
		"attack": 20,
		"strength": 20,
		"hits": 16,
		"defense": 17,
		"ranged": false,
		"combatlvl": 18,
		"isMembers": 0,
		"attackable": 0,
		"aggressive": 0
	  },{
		"id": 145,
		"name": "Shopkeeper",
		"description": "I wonder what he's got for sale",
		"command": "",
		"attack": 0,
		"strength": 0,
		"hits": 3,
		"defense": 0,
		"ranged": false,
		"combatlvl": 0,
		"isMembers": 0,
		"attackable": 0,
		"aggressive": 0
	  },{
		"id": 146,
		"name": "Shop Assistant",
		"description": "Maybe he'd like to buy some of my junk",
		"command": "",
		"attack": 0,
		"strength": 0,
		"hits": 3,
		"defense": 0,
		"ranged": false,
		"combatlvl": 0,
		"isMembers": 0,
		"attackable": 0,
		"aggressive": 0
	  },{
		"id": 147,
		"name": "Guide",
		"description": "She gives hints to new adventurers",
		"command": "",
		"attack": 0,
		"strength": 0,
		"hits": 7,
		"defense": 0,
		"ranged": false,
		"combatlvl": 1,
		"isMembers": 0,
		"attackable": 0,
		"aggressive": 0
	  },{
		"id": 148,
		"name": "Hetty",
		"description": "A witch",
		"command": "",
		"attack": 35,
		"strength": 30,
		"hits": 10,
		"defense": 25,
		"ranged": false,
		"combatlvl": 25,
		"isMembers": 0,
		"attackable": 0,
		"aggressive": 0
	  },{
		"id": 149,
		"name": "Betty",
		"description": "A witch",
		"command": "",
		"attack": 35,
		"strength": 30,
		"hits": 10,
		"defense": 25,
		"ranged": false,
		"combatlvl": 25,
		"isMembers": 0,
		"attackable": 0,
		"aggressive": 0
	  },{
		"id": 150,
		"name": "Bartender",
		"description": "I could get a beer off him",
		"command": "",
		"attack": 0,
		"strength": 0,
		"hits": 3,
		"defense": 0,
		"ranged": false,
		"combatlvl": 0,
		"isMembers": 0,
		"attackable": 0,
		"aggressive": 0
	  },{
		"id": 151,
		"name": "General wartface",
		"description": "_",
		"command": "",
		"attack": 16,
		"strength": 13,
		"hits": 12,
		"defense": 14,
		"ranged": false,
		"combatlvl": 13,
		"isMembers": 0,
		"attackable": 0,
		"aggressive": 0
	  },{
		"id": 152,
		"name": "General Bentnoze",
		"description": "_",
		"command": "",
		"attack": 16,
		"strength": 13,
		"hits": 12,
		"defense": 14,
		"ranged": false,
		"combatlvl": 13,
		"isMembers": 0,
		"attackable": 0,
		"aggressive": 0
	  },{
		"id": 153,
		"name": "Goblin",
		"description": "_",
		"command": "",
		"attack": 16,
		"strength": 13,
		"hits": 12,
		"defense": 14,
		"ranged": false,
		"combatlvl": 13,
		"isMembers": 0,
		"attackable": 1,
		"aggressive": 0
	  },{
		"id": 154,
		"name": "Goblin",
		"description": "_",
		"command": "",
		"attack": 16,
		"strength": 13,
		"hits": 12,
		"defense": 14,
		"ranged": false,
		"combatlvl": 13,
		"isMembers": 0,
		"attackable": 1,
		"aggressive": 0
	  },{
		"id": 155,
		"name": "Herquin",
		"description": "A gem merchant",
		"command": "",
		"attack": 0,
		"strength": 0,
		"hits": 3,
		"defense": 0,
		"ranged": false,
		"combatlvl": 0,
		"isMembers": 0,
		"attackable": 0,
		"aggressive": 0
	  },{
		"id": 156,
		"name": "Rommik",
		"description": "The owner of the crafting shop",
		"command": "",
		"attack": 0,
		"strength": 0,
		"hits": 3,
		"defense": 0,
		"ranged": false,
		"combatlvl": 0,
		"isMembers": 0,
		"attackable": 0,
		"aggressive": 0
	  },{
		"id": 157,
		"name": "Grum",
		"description": "Grum the goldsmith",
		"command": "",
		"attack": 0,
		"strength": 0,
		"hits": 3,
		"defense": 0,
		"ranged": false,
		"combatlvl": 0,
		"isMembers": 0,
		"attackable": 0,
		"aggressive": 0
	  }]
  }
